[
    { "key": "home", "value": "Home" },
    { "key": "consultant-hub", "value": "Consultant Hub" },
    { "key": "client-my-project", "value": "Client My Project" },
    { "key": "client-sign-project", "value": "Client Sign Project" },
    { "key": "client-setup-project", "value": "Client Setup Project" },
    { "key": "client-project-details", "value": "Client Project Details" },
    { "key": "contractor-my-project", "value": "Contractor My Project" },
    { "key": "contractor-create-project", "value": "Contractor Create Project" },
    { "key": "signup-client", "value": "Signup Client" },
    { "key": "login-client", "value": "Login Client" },

    { "key": "client-invite-consultant", "value": "Client Invite Consultant" },
    { "key": "client-notifications", "value": "Client Notifications" },
    { "key": "client-view-profile", "value": "Client View Profile" },
    { "key": "client-edit-profile", "value": "Client Edit Profile" },
    { "key": "client-create-project-tender", "value": "Client Create Project Tender" },
    { "key": "client-create-project-signproject-sign", "value": "Client Create Project Signproject Sign" },

    { "key": "signup-consultant", "value": "Signup Consultant" },
    { "key": "login-consultant", "value": "Login Consultant" },
    { "key": "consultant-my-projects", "value": "Consultant My Projects" },
    { "key": "consultant-invite-client", "value": "Consultant Invite Client" },
    { "key": "consultant-notifications", "value": "Consultant Notifications" },
    { "key": "consultant-view-profile", "value": "Consultant View Profile" },
    { "key": "consultant-edit-profile", "value": "Consultant Edit Profile" },

    { "key": "signup-contractor", "value": "Signup Contractor" },
    { "key": "login-contractor", "value": "Login Contractor" },
    { "key": "contractor-create-project-bidding", "value": "Contractor Create Project Bidding" },
    { "key": "contractor-create-project-tender", "value": "Contractor Create Project Tender" },
    { "key": "contractor-find-new-project", "value": "Contractor Find New Project" },
    { "key": "contractor-create-project-signproject", "value": "Contractor Create Project Signproject" },
    { "key": "contractor-create-project-signproject-update-contract", "value": "Contractor Create Project Signproject Update Contract" },
    { "key": "contractor-create-project-signproject-sign", "value": "Contractor Create Project Signproject Sign" },
    { "key": "contractor-create-project-signproject-reject-contract", "value": "Contractor Create Project Signproject Reject Contract" },
    { "key": "contractor-notifications", "value": "Contractor Notifications" },
    { "key": "contractor-view-profile", "value": "Contractor View Profile" },
    { "key": "contractor-edit-profile", "value": "Contractor Edit Profile" },
    { "key": "contractor-project-details", "value": "Contractor Project Details" },

    { "key": "quick-info-modal", "value": "Quick Info Modal" },
    { "key": "help-floater", "value": "Help Floater" },
    { "key": "print-stage-tasks", "value": "Print Stage Tasks" },
    { "key": "project-statuses", "value": "Project Statuses" },
    { "key": "scope-specifications", "value": "Scope Specifications" }
]
